LICENSE
aws_lambda_typing/__init__.py
aws_lambda_typing/common/__init__.py
aws_lambda_typing/common/iam.py
aws_lambda_typing/context/__init__.py
aws_lambda_typing/context/context.py
aws_lambda_typing/events/__init__.py
aws_lambda_typing/events/alb.py
aws_lambda_typing/events/apache_kafka.py
aws_lambda_typing/events/api_gateway_authorizer.py
aws_lambda_typing/events/api_gateway_proxy.py
aws_lambda_typing/events/app_sync_resolver.py
aws_lambda_typing/events/cloud_formation_custom_resource.py
aws_lambda_typing/events/cloud_watch_events.py
aws_lambda_typing/events/cloud_watch_logs.py
aws_lambda_typing/events/code_commit.py
aws_lambda_typing/events/code_pipeline.py
aws_lambda_typing/events/cognito_custom_message.py
aws_lambda_typing/events/cognito_post_confirmation.py
aws_lambda_typing/events/config.py
aws_lambda_typing/events/dynamodb_stream.py
aws_lambda_typing/events/ec2_asg_custom_termination_policy.py
aws_lambda_typing/events/event_bridge.py
aws_lambda_typing/events/iot.py
aws_lambda_typing/events/kinesis_firehose.py
aws_lambda_typing/events/kinesis_stream.py
aws_lambda_typing/events/mq.py
aws_lambda_typing/events/msk.py
aws_lambda_typing/events/s3.py
aws_lambda_typing/events/s3_batch.py
aws_lambda_typing/events/secrets_manager.py
aws_lambda_typing/events/ses.py
aws_lambda_typing/events/sns.py
aws_lambda_typing/events/sqs.py
aws_lambda_typing/events/websocket.py
aws_lambda_typing/py.typed
aws_lambda_typing/requests/__init__.py
aws_lambda_typing/requests/sns.py
aws_lambda_typing/responses/__init__.py
aws_lambda_typing/responses/alb.py
aws_lambda_typing/responses/api_gateway_authorizer.py
aws_lambda_typing/responses/api_gateway_proxy.py
aws_lambda_typing/responses/dynamodb_batch.py
aws_lambda_typing/responses/iot.py
aws_lambda_typing/responses/kinesis_firehose.py
aws_lambda_typing/responses/s3_batch.py
aws_lambda_typing-2.19.0.dist-info/LICENSE
aws_lambda_typing-2.19.0.dist-info/WHEEL
aws_lambda_typing-2.19.0.dist-info/METADATA
aws_lambda_typing-2.19.0.dist-info/RECORD
