Metadata-Version: 2.1
Name: aws-lambda-typing
Version: 2.19.0
Summary: A package that provides type hints for AWS Lambda event, context and response objects
Home-page: https://github.com/MousaZeidBaker/aws-lambda-typing
License: MIT
Keywords: typing,type hints,aws,lambda,serverless,development
Author: Mousa Zeid Baker
Requires-Python: >=3.6,<4.0
Classifier: Development Status :: 5 - Production/Stable
Classifier: License :: OSI Approved :: MIT License
Classifier: Operating System :: OS Independent
Classifier: Programming Language :: Python :: 3
Classifier: Programming Language :: Python :: 3.6
Classifier: Programming Language :: Python :: 3.7
Classifier: Programming Language :: Python :: 3.8
Classifier: Programming Language :: Python :: 3.9
Classifier: Programming Language :: Python :: 3.10
Classifier: Programming Language :: Python :: 3
Requires-Dist: typing-extensions (>=4.1.1,<5.0.0); python_version < "3.8"
Project-URL: Repository, https://github.com/MousaZeidBaker/aws-lambda-typing
